{
	"id": "TVoHIefFfVuWigl",
	"json": "{\"id\":\"TVoHIefFfVuWigl\",\"url\":\"https://salcobrand.cl/products/tisse-crema-corporal-250ml\",\"uniqueKey\":\"https://salcobrand.cl/products/tisse-crema-corporal-250ml\",\"method\":\"GET\",\"noRetry\":false,\"retryCount\":0,\"errorMessages\":[],\"headers\":{},\"userData\":{}}",
	"method": "GET",
	"orderNo": 1737052719034,
	"retryCount": 0,
	"uniqueKey": "https://salcobrand.cl/products/tisse-crema-corporal-250ml",
	"url": "https://salcobrand.cl/products/tisse-crema-corporal-250ml"
}