{
	"id": "0l7RCFWpbbKStk4",
	"json": "{\"id\":\"0l7RCFWpbbKStk4\",\"url\":\"https://www.cruzverde.cl/talco-en-spray-100-gr/13241.html\",\"uniqueKey\":\"https://www.cruzverde.cl/talco-en-spray-100-gr/13241.html\",\"method\":\"GET\",\"noRetry\":false,\"retryCount\":0,\"errorMessages\":[],\"headers\":{},\"userData\":{}}",
	"method": "GET",
	"orderNo": 1737052932074,
	"retryCount": 0,
	"uniqueKey": "https://www.cruzverde.cl/talco-en-spray-100-gr/13241.html",
	"url": "https://www.cruzverde.cl/talco-en-spray-100-gr/13241.html"
}