{
	"id": "3CwRQRHalWFtSjB",
	"json": "{\"id\":\"3CwRQRHalWFtSjB\",\"url\":\"https://www.cruzverde.cl/rejuveness-crema-de-200-gr/253182.html\",\"uniqueKey\":\"https://www.cruzverde.cl/rejuveness-crema-de-200-gr/253182.html\",\"method\":\"GET\",\"noRetry\":false,\"retryCount\":0,\"errorMessages\":[],\"headers\":{},\"userData\":{}}",
	"method": "GET",
	"orderNo": 1737052938807,
	"retryCount": 0,
	"uniqueKey": "https://www.cruzverde.cl/rejuveness-crema-de-200-gr/253182.html",
	"url": "https://www.cruzverde.cl/rejuveness-crema-de-200-gr/253182.html"
}