{
	"id": "5nuiAmH4BPNivQW",
	"json": "{\"id\":\"5nuiAmH4BPNivQW\",\"url\":\"https://www.cruzverde.cl/shampoo-bomba-detox-340-ml/264925.html\",\"uniqueKey\":\"https://www.cruzverde.cl/shampoo-bomba-detox-340-ml/264925.html\",\"method\":\"GET\",\"noRetry\":false,\"retryCount\":0,\"errorMessages\":[],\"headers\":{},\"userData\":{}}",
	"method": "GET",
	"orderNo": 1737052944695,
	"retryCount": 0,
	"uniqueKey": "https://www.cruzverde.cl/shampoo-bomba-detox-340-ml/264925.html",
	"url": "https://www.cruzverde.cl/shampoo-bomba-detox-340-ml/264925.html"
}