{
	"id": "6GWmrKYiFG2fRdg",
	"json": "{\"id\":\"6GWmrKYiFG2fRdg\",\"url\":\"https://www.cruzverde.cl/shampoo-anticaspa-normal-mx/208046.html\",\"uniqueKey\":\"https://www.cruzverde.cl/shampoo-anticaspa-normal-mx/208046.html\",\"method\":\"GET\",\"noRetry\":false,\"retryCount\":0,\"errorMessages\":[],\"headers\":{},\"userData\":{}}",
	"method": "GET",
	"orderNo": 1737052938169,
	"retryCount": 0,
	"uniqueKey": "https://www.cruzverde.cl/shampoo-anticaspa-normal-mx/208046.html",
	"url": "https://www.cruzverde.cl/shampoo-anticaspa-normal-mx/208046.html"
}