{
	"id": "euJB6vQhZlhSqT0",
	"json": "{\"id\":\"euJB6vQhZlhSqT0\",\"url\":\"https://www.cruzverde.cl/drontal-cats-2-comprimidos/152133.html\",\"uniqueKey\":\"https://www.cruzverde.cl/drontal-cats-2-comprimidos/152133.html\",\"method\":\"GET\",\"noRetry\":false,\"retryCount\":0,\"errorMessages\":[],\"headers\":{},\"userData\":{}}",
	"method": "GET",
	"orderNo": 1737052935671,
	"retryCount": 0,
	"uniqueKey": "https://www.cruzverde.cl/drontal-cats-2-comprimidos/152133.html",
	"url": "https://www.cruzverde.cl/drontal-cats-2-comprimidos/152133.html"
}