{
	"id": "HtA1qvwmpYTEujA",
	"json": "{\"id\":\"HtA1qvwmpYTEujA\",\"url\":\"https://www.cruzverde.cl/comprimido-2-tone-20-unidades/258361.html\",\"uniqueKey\":\"https://www.cruzverde.cl/comprimido-2-tone-20-unidades/258361.html\",\"method\":\"GET\",\"noRetry\":false,\"retryCount\":0,\"errorMessages\":[],\"headers\":{},\"userData\":{}}",
	"method": "GET",
	"orderNo": 1737052941397,
	"retryCount": 0,
	"uniqueKey": "https://www.cruzverde.cl/comprimido-2-tone-20-unidades/258361.html",
	"url": "https://www.cruzverde.cl/comprimido-2-tone-20-unidades/258361.html"
}