{
	"id": "OAy52i4wo9O7t3d",
	"json": "{\"id\":\"OAy52i4wo9O7t3d\",\"url\":\"https://www.cruzverde.cl/eau-de-parfum-hot-in-black-80-ml/258911.html\",\"uniqueKey\":\"https://www.cruzverde.cl/eau-de-parfum-hot-in-black-80-ml/258911.html\",\"method\":\"GET\",\"noRetry\":false,\"retryCount\":0,\"errorMessages\":[],\"headers\":{},\"userData\":{}}",
	"method": "GET",
	"orderNo": 1737052941455,
	"retryCount": 0,
	"uniqueKey": "https://www.cruzverde.cl/eau-de-parfum-hot-in-black-80-ml/258911.html",
	"url": "https://www.cruzverde.cl/eau-de-parfum-hot-in-black-80-ml/258911.html"
}