{
	"id": "Q9PeyISJ2Nchs04",
	"json": "{\"id\":\"Q9PeyISJ2Nchs04\",\"url\":\"https://www.cruzverde.cl/toalla-facial-hidra-total5/134236.html\",\"uniqueKey\":\"https://www.cruzverde.cl/toalla-facial-hidra-total5/134236.html\",\"method\":\"GET\",\"noRetry\":false,\"retryCount\":0,\"errorMessages\":[],\"headers\":{},\"userData\":{}}",
	"method": "GET",
	"orderNo": 1737052935259,
	"retryCount": 0,
	"uniqueKey": "https://www.cruzverde.cl/toalla-facial-hidra-total5/134236.html",
	"url": "https://www.cruzverde.cl/toalla-facial-hidra-total5/134236.html"
}