{
	"id": "QHEFInEafNtuoMU",
	"json": "{\"id\":\"QHEFInEafNtuoMU\",\"url\":\"https://www.cruzverde.cl/avena-jabon-liquido-de--700-ml/260188.html\",\"uniqueKey\":\"https://www.cruzverde.cl/avena-jabon-liquido-de--700-ml/260188.html\",\"method\":\"GET\",\"noRetry\":false,\"retryCount\":0,\"errorMessages\":[],\"headers\":{},\"userData\":{}}",
	"method": "GET",
	"orderNo": 1737052941937,
	"retryCount": 0,
	"uniqueKey": "https://www.cruzverde.cl/avena-jabon-liquido-de--700-ml/260188.html",
	"url": "https://www.cruzverde.cl/avena-jabon-liquido-de--700-ml/260188.html"
}