{
	"id": "sYCpeyBs9417OHZ",
	"json": "{\"id\":\"sYCpeyBs9417OHZ\",\"url\":\"https://www.cruzverde.cl/cinta-adhesiva-micropore-blanca-12.5-mm-x-9.1-mts/160008.html\",\"uniqueKey\":\"https://www.cruzverde.cl/cinta-adhesiva-micropore-blanca-12.5-mm-x-9.1-mts/160008.html\",\"method\":\"GET\",\"noRetry\":false,\"retryCount\":0,\"errorMessages\":[],\"headers\":{},\"userData\":{}}",
	"method": "GET",
	"orderNo": 1737052936071,
	"retryCount": 0,
	"uniqueKey": "https://www.cruzverde.cl/cinta-adhesiva-micropore-blanca-12.5-mm-x-9.1-mts/160008.html",
	"url": "https://www.cruzverde.cl/cinta-adhesiva-micropore-blanca-12.5-mm-x-9.1-mts/160008.html"
}