{
	"id": "t2I9i8Iyq7XBinD",
	"json": "{\"id\":\"t2I9i8Iyq7XBinD\",\"url\":\"https://www.cruzverde.cl/cartera-espejo/258131.html\",\"uniqueKey\":\"https://www.cruzverde.cl/cartera-espejo/258131.html\",\"method\":\"GET\",\"noRetry\":false,\"retryCount\":0,\"errorMessages\":[],\"headers\":{},\"userData\":{}}",
	"method": "GET",
	"orderNo": 1737052941362,
	"retryCount": 0,
	"uniqueKey": "https://www.cruzverde.cl/cartera-espejo/258131.html",
	"url": "https://www.cruzverde.cl/cartera-espejo/258131.html"
}