{
	"id": "x1rghUpF4k53KDz",
	"json": "{\"id\":\"x1rghUpF4k53KDz\",\"url\":\"https://www.cruzverde.cl/crema-anti-rojeces-roseliane-40ml/268310.html\",\"uniqueKey\":\"https://www.cruzverde.cl/crema-anti-rojeces-roseliane-40ml/268310.html\",\"method\":\"GET\",\"noRetry\":false,\"retryCount\":0,\"errorMessages\":[],\"headers\":{},\"userData\":{}}",
	"method": "GET",
	"orderNo": 1737052945623,
	"retryCount": 0,
	"uniqueKey": "https://www.cruzverde.cl/crema-anti-rojeces-roseliane-40ml/268310.html",
	"url": "https://www.cruzverde.cl/crema-anti-rojeces-roseliane-40ml/268310.html"
}