{
	"id": "X1ZbobuS5UAu3q8",
	"json": "{\"id\":\"X1ZbobuS5UAu3q8\",\"url\":\"https://www.cruzverde.cl/bencilpenicilina-sodica-2.000.000-ui-1-ampolla/199251.html\",\"uniqueKey\":\"https://www.cruzverde.cl/bencilpenicilina-sodica-2.000.000-ui-1-ampolla/199251.html\",\"method\":\"GET\",\"noRetry\":false,\"retryCount\":0,\"errorMessages\":[],\"headers\":{},\"userData\":{}}",
	"method": "GET",
	"orderNo": 1737052938055,
	"retryCount": 0,
	"uniqueKey": "https://www.cruzverde.cl/bencilpenicilina-sodica-2.000.000-ui-1-ampolla/199251.html",
	"url": "https://www.cruzverde.cl/bencilpenicilina-sodica-2.000.000-ui-1-ampolla/199251.html"
}