{
	"id": "XRCndYbgkBOGKVD",
	"json": "{\"id\":\"XRCndYbgkBOGKVD\",\"url\":\"https://www.cruzverde.cl/talco-fresh-120-gr/97031.html\",\"uniqueKey\":\"https://www.cruzverde.cl/talco-fresh-120-gr/97031.html\",\"method\":\"GET\",\"noRetry\":false,\"retryCount\":0,\"errorMessages\":[],\"headers\":{},\"userData\":{}}",
	"method": "GET",
	"orderNo": 1737052934334,
	"retryCount": 0,
	"uniqueKey": "https://www.cruzverde.cl/talco-fresh-120-gr/97031.html",
	"url": "https://www.cruzverde.cl/talco-fresh-120-gr/97031.html"
}