{
	"id": "HjNtRNFjeQoHTBg",
	"json": "{\"id\":\"HjNtRNFjeQoHTBg\",\"url\":\"https://www.drsimi.cl/crotamiton-10-60ml-locion/p\",\"loadedUrl\":\"https://www.drsimi.cl/crotamiton-10-60ml-locion/p\",\"uniqueKey\":\"https://www.drsimi.cl/crotamiton-10-60ml-locion/p\",\"method\":\"GET\",\"noRetry\":false,\"retryCount\":0,\"errorMessages\":[],\"headers\":{},\"userData\":{\"__crawlee\":{\"state\":4}},\"handledAt\":\"2024-12-12T20:33:53.679Z\"}",
	"method": "GET",
	"orderNo": null,
	"retryCount": 0,
	"uniqueKey": "https://www.drsimi.cl/crotamiton-10-60ml-locion/p",
	"url": "https://www.drsimi.cl/crotamiton-10-60ml-locion/p"
}