{
	"id": "BQI7wu3X7xbGsX2",
	"json": "{\"id\":\"BQI7wu3X7xbGsX2\",\"url\":\"https://salcobrand.cl/products/serum-anti-edad-restore-r-10\",\"uniqueKey\":\"https://salcobrand.cl/products/serum-anti-edad-restore-r-10\",\"method\":\"GET\",\"noRetry\":false,\"retryCount\":0,\"errorMessages\":[],\"headers\":{},\"userData\":{}}",
	"method": "GET",
	"orderNo": 1737054313688,
	"retryCount": 0,
	"uniqueKey": "https://salcobrand.cl/products/serum-anti-edad-restore-r-10",
	"url": "https://salcobrand.cl/products/serum-anti-edad-restore-r-10"
}