{
	"id": "G6WWQmdIMepA2EW",
	"json": "{\"id\":\"G6WWQmdIMepA2EW\",\"url\":\"https://salcobrand.cl/products/matcha-luxurious-face-wash\",\"uniqueKey\":\"https://salcobrand.cl/products/matcha-luxurious-face-wash\",\"method\":\"GET\",\"noRetry\":false,\"retryCount\":0,\"errorMessages\":[],\"headers\":{},\"userData\":{}}",
	"method": "GET",
	"orderNo": 1737054313740,
	"retryCount": 0,
	"uniqueKey": "https://salcobrand.cl/products/matcha-luxurious-face-wash",
	"url": "https://salcobrand.cl/products/matcha-luxurious-face-wash"
}